algorithmz/__init__.py
algorithmz/core.py
algorithmz-0.1.0.dist-info/METADATA
algorithmz-0.1.0.dist-info/WHEEL
algorithmz-0.1.0.dist-info/top_level.txt
algorithmz-0.1.0.dist-info/RECORD
